ble/__init__.py
ble/client.py
ble/scanner.py
ble/utils.py
devices/__init__.py
devices/led.py
devices/motor.py
pylegollm-0.1.0.dist-info/LICENSE
pylegollm-0.1.0.dist-info/METADATA
pylegollm-0.1.0.dist-info/WHEEL
pylegollm-0.1.0.dist-info/top_level.txt
pylegollm-0.1.0.dist-info/RECORD
