Metadata-Version: 2.2
Name: pyLegoLLM
Version: 0.1.0
Summary: A Python package to control LEGO bricks via BLE.
Author: tnl2rgn2
Author-email: tnl2rgn2@example.com
Classifier: Programming Language :: Python :: 3
Classifier: License :: OSI Approved :: MIT License
Classifier: Operating System :: OS Independent
Requires-Python: >=3.7
License-File: LICENSE
Requires-Dist: bleak
Dynamic: author
Dynamic: author-email
Dynamic: classifier
Dynamic: requires-dist
Dynamic: requires-python
Dynamic: summary
